[
 {
  "T": 1.63287,
  "Q": 0.01064
 },
 {
  "T": 4.12079,
  "Q": 0.01066
 },
 {
  "T": 6.79262,
  "Q": 0.01067
 },
 {
  "T": 9.44927,
  "Q": 0.01061
 },
 {
  "T": 12.4225,
  "Q": 0.01051
 },
 {
  "T": 15.49121,
  "Q": 0.01056
 },
 {
  "T": 18.29201,
  "Q": 0.01057
 },
 {
  "T": 20.92216,
  "Q": 0.01057
 },
 {
  "T": 23.58816,
  "Q": 0.01054
 },
 {
  "T": 26.55919,
  "Q": 0.01052
 },
 {
  "T": 29.40174,
  "Q": 0.01048
 },
 {
  "T": 32.2247,
  "Q": 0.01047
 },
 {
  "T": 35.03582,
  "Q": 0.01046
 },
 {
  "T": 37.85718,
  "Q": 0.01041
 },
 {
  "T": 40.6764,
  "Q": 0.01038
 },
 {
  "T": 43.49644,
  "Q": 0.01031
 },
 {
  "T": 46.31519,
  "Q": 0.01023
 },
 {
  "T": 49.14626,
  "Q": 0.01017
 },
 {
  "T": 51.94031,
  "Q": 0.01011
 },
 {
  "T": 54.78193,
  "Q": 0.01009
 },
 {
  "T": 57.59604,
  "Q": 0.01003
 },
 {
  "T": 60.42211,
  "Q": 0.00999
 },
 {
  "T": 63.23877,
  "Q": 0.00994
 },
 {
  "T": 66.04504,
  "Q": 0.00991
 },
 {
  "T": 68.87361,
  "Q": 0.00987
 },
 {
  "T": 71.68684,
  "Q": 0.00984
 },
 {
  "T": 74.52022,
  "Q": 0.00982
 },
 {
  "T": 77.35421,
  "Q": 0.0098
 },
 {
  "T": 80.16109,
  "Q": 0.00982
 },
 {
  "T": 82.99084,
  "Q": 0.00984
 },
 {
  "T": 85.80004,
  "Q": 0.00986
 },
 {
  "T": 88.62738,
  "Q": 0.00993
 },
 {
  "T": 91.44049,
  "Q": 0.00998
 },
 {
  "T": 94.27954,
  "Q": 0.01005
 },
 {
  "T": 97.08215,
  "Q": 0.01012
 },
 {
  "T": 99.91219,
  "Q": 0.01017
 },
 {
  "T": 102.7332,
  "Q": 0.01023
 },
 {
  "T": 105.5494,
  "Q": 0.01031
 },
 {
  "T": 108.3664,
  "Q": 0.01041
 },
 {
  "T": 111.1984,
  "Q": 0.01047
 },
 {
  "T": 114.0116,
  "Q": 0.01055
 },
 {
  "T": 116.8425,
  "Q": 0.01066
 },
 {
  "T": 119.6579,
  "Q": 0.01077
 },
 {
  "T": 122.4798,
  "Q": 0.01088
 },
 {
  "T": 125.3068,
  "Q": 0.01098
 },
 {
  "T": 128.1281,
  "Q": 0.01113
 },
 {
  "T": 130.94,
  "Q": 0.01129
 },
 {
  "T": 133.762,
  "Q": 0.01144
 },
 {
  "T": 136.5862,
  "Q": 0.01163
 },
 {
  "T": 139.4053,
  "Q": 0.01177
 },
 {
  "T": 142.2249,
  "Q": 0.01187
 },
 {
  "T": 145.0489,
  "Q": 0.01201
 },
 {
  "T": 147.8763,
  "Q": 0.01213
 },
 {
  "T": 150.69,
  "Q": 0.01223
 },
 {
  "T": 153.5147,
  "Q": 0.01232
 },
 {
  "T": 156.3388,
  "Q": 0.01242
 },
 {
  "T": 159.157,
  "Q": 0.01251
 },
 {
  "T": 161.9846,
  "Q": 0.01259
 },
 {
  "T": 164.806,
  "Q": 0.01263
 },
 {
  "T": 167.6202,
  "Q": 0.0127
 },
 {
  "T": 170.4458,
  "Q": 0.01276
 },
 {
  "T": 173.2716,
  "Q": 0.01281
 },
 {
  "T": 176.0958,
  "Q": 0.01283
 },
 {
  "T": 178.9057,
  "Q": 0.01282
 },
 {
  "T": 181.7328,
  "Q": 0.0128
 },
 {
  "T": 184.5541,
  "Q": 0.01276
 },
 {
  "T": 187.3719,
  "Q": 0.01271
 },
 {
  "T": 190.1946,
  "Q": 0.01262
 },
 {
  "T": 193.0171,
  "Q": 0.01251
 },
 {
  "T": 195.8406,
  "Q": 0.01237
 },
 {
  "T": 198.6617,
  "Q": 0.01222
 },
 {
  "T": 201.4894,
  "Q": 0.01206
 },
 {
  "T": 204.3038,
  "Q": 0.01187
 },
 {
  "T": 207.1238,
  "Q": 0.01165
 },
 {
  "T": 209.9462,
  "Q": 0.01142
 },
 {
  "T": 212.7707,
  "Q": 0.01117
 },
 {
  "T": 215.5932,
  "Q": 0.01086
 },
 {
  "T": 218.4125,
  "Q": 0.01056
 },
 {
  "T": 221.2315,
  "Q": 0.01025
 },
 {
  "T": 224.0549,
  "Q": 0.00993
 },
 {
  "T": 226.8754,
  "Q": 0.00959
 },
 {
  "T": 229.6942,
  "Q": 0.00925
 },
 {
  "T": 232.5253,
  "Q": 0.0089
 },
 {
  "T": 235.347,
  "Q": 0.00853
 },
 {
  "T": 238.1667,
  "Q": 0.00817
 },
 {
  "T": 240.981,
  "Q": 0.00778
 },
 {
  "T": 243.8085,
  "Q": 0.00743
 },
 {
  "T": 246.6373,
  "Q": 0.00705
 },
 {
  "T": 249.4539,
  "Q": 0.00668
 },
 {
  "T": 252.2736,
  "Q": 0.00629
 },
 {
  "T": 255.0913,
  "Q": 0.00592
 },
 {
  "T": 257.9156,
  "Q": 0.00558
 },
 {
  "T": 260.7348,
  "Q": 0.00523
 },
 {
  "T": 263.5516,
  "Q": 0.0049
 },
 {
  "T": 266.3845,
  "Q": 0.00459
 },
 {
  "T": 269.1912,
  "Q": 0.00431
 },
 {
  "T": 272.0256,
  "Q": 0.00404
 },
 {
  "T": 274.846,
  "Q": 0.00384
 },
 {
  "T": 277.6642,
  "Q": 0.00365
 },
 {
  "T": 280.492,
  "Q": 0.00345
 },
 {
  "T": 283.3053,
  "Q": 0.0033
 },
 {
  "T": 286.1322,
  "Q": 0.00314
 },
 {
  "T": 288.9518,
  "Q": 0.00303
 },
 {
  "T": 291.7686,
  "Q": 0.00294
 },
 {
  "T": 294.5846,
  "Q": 0.00285
 },
 {
  "T": 297.4108,
  "Q": 0.00278
 },
 {
  "T": 300.25,
  "Q": 0.00271
 },
 {
  "T": 303.0636,
  "Q": 0.00262
 }
]